Metadata-Version: 2.1
Name: BABAIJEBU
Version: 1.2
Summary:  Baba Ijebu is a game that allows it users to guess a random number from 0-10 setting thier trial number optionaly
Author: ALADETOYINBO GBEMISOLA IBIERE
Author-email: megbopegbemisola96@gmail.com
License-File: license.tet
